nt25/__init__.py
nt25/mt.py
nt25/pgogs.py
nt25/data/exif.jpg
nt25/data/gogs.sql
nt25/lib/exif.py
nt25/lib/fio.py
nt25/lib/sqlite.py
nt25-1.0.5.dist-info/METADATA
nt25-1.0.5.dist-info/WHEEL
nt25-1.0.5.dist-info/entry_points.txt
nt25-1.0.5.dist-info/RECORD
