Metadata-Version: 2.4
Name: nt25
Version: 1.0.5
Summary: Neo's Tools of Python
Requires-Python: >=3.10
Requires-Dist: pillow>=11.3.0
Requires-Dist: pyinstaller>=6.16.0
Requires-Dist: requests>=2.32.5
